mmf_setup/__init__.py
mmf_setup/notebook_configuration.py
mmf_setup/_data/hgrc.full
mmf_setup/_data/hgrc.lga
mmf_setup/_data/mrconfig
mmf_setup/_data/nbclean.hgrc
mmf_setup/_data/config_files/cocalc/README.md
mmf_setup/_data/config_files/cocalc/bash_aliases
mmf_setup/_data/config_files/cocalc/bashrc
mmf_setup/_data/config_files/cocalc/gitconfig
mmf_setup/_data/config_files/cocalc/gitignore
mmf_setup/_data/config_files/cocalc/hgignore
mmf_setup/_data/config_files/cocalc/hgrc
mmf_setup/_data/config_files/cocalc/inputrc
mmf_setup/_data/config_files/cocalc/message.txt
mmf_setup/_data/config_files/cocalc/mr
mmf_setup/_data/config_files/cocalc/mrconfig
mmf_setup/_data/config_files/cocalc/pdbrc
mmf_setup/_data/nbthemes/default.css
mmf_setup/_data/nbthemes/default.html
mmf_setup/_data/nbthemes/default.js
mmf_setup/_data/nbthemes/default.tex
mmf_setup/_data/nbthemes/mmf.css
mmf_setup/_data/nbthemes/mmf.js
mmf_setup/set_path/__init__.py
mmf_setup/set_path/hgroot.py
mmf_setup-0.4.12.data/scripts/mmf_initial_setup
mmf_setup-0.4.12.data/scripts/mmf_setup
mmf_setup-0.4.12.data/scripts/mmf_setup_bash.py
mmf_setup-0.4.12.dist-info/LICENSE.txt
mmf_setup-0.4.12.dist-info/METADATA
mmf_setup-0.4.12.dist-info/WHEEL
mmf_setup-0.4.12.dist-info/top_level.txt
mmf_setup-0.4.12.dist-info/RECORD
