Metadata-Version: 2.1
Name: mmf_setup
Version: 0.4.12
Summary: Meta-package to quickly initialize my python environment.
Author-email: Michael McNeil Forbes <michael.forbes+python@gmail.com>
License: BSD-3-Clause
Keywords: ipython,jupyter,notebook,setup,mercurial
Classifier: Development Status :: 4 - Beta
Classifier: Intended Audience :: Developers
Classifier: Topic :: Software Development :: Libraries :: Python Modules
Classifier: Topic :: Utilities
Requires-Python: >=3.8
License-File: LICENSE.txt
Requires-Dist: tomlkit >=0.7.2
Requires-Dist: importlib-metadata ; python_version < "3.10"
Provides-Extra: hg
Requires-Dist: mercurial >=5.9.2 ; extra == 'hg'
Requires-Dist: hg-evolve >=10.4.0 ; extra == 'hg'
Requires-Dist: hg-git >=0.10.2 ; extra == 'hg'
Provides-Extra: mercurial
Requires-Dist: mercurial >=5.9.2 ; extra == 'mercurial'
Requires-Dist: hg-evolve >=10.4.0 ; extra == 'mercurial'
Requires-Dist: hg-git >=0.10.2 ; extra == 'mercurial'
Provides-Extra: nbextensions
Requires-Dist: jupyter-contrib-nbextensions ; extra == 'nbextensions'
Provides-Extra: test
Requires-Dist: notebook ; extra == 'test'
Requires-Dist: pytest >=2.8.1 ; extra == 'test'
Requires-Dist: pytest-cov >=3.0.0 ; extra == 'test'
Requires-Dist: pytest-flake8 >=1.0.7 ; extra == 'test'
Requires-Dist: pytest-xdist >=2.4.0 ; extra == 'test'
Requires-Dist: coverage ; extra == 'test'
Requires-Dist: mercurial ; extra == 'test'
Requires-Dist: hg-evolve ; extra == 'test'
Requires-Dist: hg-git ; extra == 'test'
Requires-Dist: twine ; extra == 'test'
Requires-Dist: docutils ; extra == 'test'
Requires-Dist: pipx ; extra == 'test'
